MANIFEST.in
README.rst
setup.py
django_slack_notification.egg-info/PKG-INFO
django_slack_notification.egg-info/SOURCES.txt
django_slack_notification.egg-info/dependency_links.txt
django_slack_notification.egg-info/requires.txt
django_slack_notification.egg-info/top_level.txt
django_slack_notifications/__init__.py
django_slack_notifications/admin.py
django_slack_notifications/apps.py
django_slack_notifications/models.py
django_slack_notifications/settings.py
django_slack_notifications/tests.py
django_slack_notifications/utils.py
django_slack_notifications/views.py
django_slack_notifications/migrations/__init__.py